moat/util/__init__.py
moat/util/_cbor.py
moat/util/_main.py
moat/util/_merge.py
moat/util/_msgpack.py
moat/util/_trio.py
moat/util/cbor.py
moat/util/ctx.py
moat/util/dict.py
moat/util/event.py
moat/util/exc.py
moat/util/exec.py
moat/util/impl.py
moat/util/inexact.py
moat/util/liner.py
moat/util/misc.py
moat/util/module.py
moat/util/msg.py
moat/util/msgpack.py
moat/util/outcome.py
moat/util/path.py
moat/util/pp.py
moat/util/queue.py
moat/util/random.py
moat/util/server.py
moat/util/spawn.py
moat/util/systemd.py
moat/util/times.py
moat/util/yaml.py
moat_util-0.62.2.dist-info/licenses/LICENSE.txt
moat_util-0.62.2.dist-info/METADATA
moat_util-0.62.2.dist-info/WHEEL
moat_util-0.62.2.dist-info/top_level.txt
moat_util-0.62.2.dist-info/RECORD
